README.rst
setup.py
config/package-managers.ini
platform_migrator/__init__.py
platform_migrator/base_sys_script.py
platform_migrator/main.py
platform_migrator/migrator.py
platform_migrator/package_manager.py
platform_migrator/server.py
platform_migrator/unpack.py
platform_migrator.egg-info/PKG-INFO
platform_migrator.egg-info/SOURCES.txt
platform_migrator.egg-info/dependency_links.txt
platform_migrator.egg-info/entry_points.txt
platform_migrator.egg-info/requires.txt
platform_migrator.egg-info/top_level.txt