Metadata-Version: 1.1
Name: platform-migrator
Version: 1.1.0
Summary: Migrate software from one system to another
Home-page: https://gitlab.com/mmc691/platform-migrator
Author: Munir Contractor
Author-email: mmc691@nyu.edu
License: MIT
Download-URL: https://gitlab.com/mmc691/platform-migrator/
Platform: any
Classifier: Development Status :: 4 - Beta
Classifier: Intended Audience :: Developers
Classifier: Intended Audience :: Science/Research
Classifier: License :: OSI Approved :: MIT License
Classifier: Operating System :: POSIX
Classifier: Operating System :: MacOS
Classifier: Operating System :: Microsoft :: Windows
Classifier: Programming Language :: Python :: 3.5
Classifier: Programming Language :: Python :: 3.6
Classifier: Topic :: Software Development :: Testing
Classifier: Topic :: System :: Software Distribution
Classifier: Topic :: Utilities
